naijalingo_asr/__init__.py
naijalingo_asr/audio.py
naijalingo_asr/cli.py
naijalingo_asr/engine.py
naijalingo_asr/logging_utils.py
naijalingo_asr/registry.py
naijalingo_asr/transcriber.py
naijalingo_asr-0.1.2.dist-info/METADATA
naijalingo_asr-0.1.2.dist-info/WHEEL
naijalingo_asr-0.1.2.dist-info/entry_points.txt
naijalingo_asr-0.1.2.dist-info/top_level.txt
naijalingo_asr-0.1.2.dist-info/RECORD
