Metadata-Version: 2.4
Name: naijalingo-asr
Version: 0.1.2
Summary: Automatic Speech Recognition (ASR) SDK for Nigerian languages Yoruba, Igbo, Hausa, and Nigerian-accented English using CTranslate2-converted Whisper models
Author: NaijaLingo
License: MIT
Project-URL: Homepage, https://pypi.org/project/naijalingo-asr/
Project-URL: Source, https://github.com/chukypedro/naijalingo-asr
Project-URL: Issues, https://github.com/chukypedro/naijalingo-asr/issues
Keywords: ASR,speech recognition,automatic speech recognition,Nigerian languages,Yoruba,Igbo,Hausa,Nigerian English,faster-whisper,ctranslate2,whisper,transcription
Classifier: Development Status :: 3 - Alpha
Classifier: Intended Audience :: Developers
Classifier: License :: OSI Approved :: MIT License
Classifier: Programming Language :: Python
Classifier: Programming Language :: Python :: 3
Classifier: Programming Language :: Python :: 3.9
Classifier: Topic :: Scientific/Engineering :: Artificial Intelligence
Classifier: Topic :: Multimedia :: Sound/Audio :: Speech
Classifier: Natural Language :: English
Requires-Python: >=3.9
Requires-Dist: faster-whisper>=1.2.0
Requires-Dist: ctranslate2>=4.6.0
Requires-Dist: librosa>=0.11.0
Requires-Dist: numpy>=1.23
Provides-Extra: audio
Requires-Dist: imageio-ffmpeg>=0.6.0; extra == "audio"
